{"type": "Feature", "id": 12523895, "properties": {"woe:id": 12523895, "woe:parent_id": 980409, "woe:name": "Patreksfjordur Airport", "woe:placetype": 14, "woe:placetype_name": "Airport", "woe:lang": "ENG", "iso:country": "IS", "meta:provider": ["geoplanet:7.3.1", "geoplanet:7.3.2", "geoplanet:7.4.0", "geoplanet:7.4.1", "geoplanet:7.5.1", "geoplanet:7.5.2", "geoplanet:7.6.0", "geoplanet:7.8.1", "geoplanet:7.9.0", "geoplanet:7.10.0", "geoplanet:8.0.0", "woeplanet:8.0.0"], "meta:indexed": "2020-08-20T20:29:18.315327", "woe:alias_ENG_V": ["PFJ Airport", "PFJ"], "meta:updated": "2020-08-22T02:50:53.703521", "woe:hierarchy": {"continent": 24865675, "country": 23424845, "town": 0, "planet": 1, "county": 0, "suburb": 0, "state": 2345706, "region": 0, "localadmin": 0}, "woe:timezone_id": 28350873, "woe:hash": "g7wuyt3fqpt6", "woe:centroid": [-23.9695, 65.551727], "geom:latitude": 65.551727, "geom:longitude": -23.9695, "geom:hash": "g7wuyt3fqpt6", "woe:latitude": 65.551727, "geom:centroid": [-23.9695, 65.551727], "woe:longitude": -23.9695, "woe:repo": "woeplanet-airport-is"}, "geometry": {"coordinates": [-23.9695, 65.551727], "type": "Point"}}